{"bundle":{"client_time":{"wall_time_millis":"1659719581831","timer_millis":"65081","timer_realtime_millis":"65081"},"pointer_data":[{"determined_at":"64083","type":"MOUSE","delta":{},"position":{"dx":1038.9287109375,"dy":818.984130859375},"pressure_range":{"upper_bound":1.0},"radius_major":0.5,"radius_minor":0.5,"size":1.0,"viewport_boundary_status":"ENTER_VIEWPORT"},{"determined_at":"64930","type":"MOUSE","delta":{},"position":{"dx":1038.682861328125,"dy":818.984130859375},"pressure_range":{"upper_bound":1.0},"radius_major":0.5,"radius_minor":0.5,"size":1.0,"viewport_boundary_status":"IN_VIEWPORT"},{"determined_at":"64945","type":"MOUSE","delta":{},"position":{"dx":1038.43701171875,"dy":818.984130859375},"pressure_range":{"upper_bound":1.0},"radius_major":0.5,"radius_minor":0.5,"size":1.0,"viewport_boundary_status":"IN_VIEWPORT"},{"determined_at":"64960","type":"MOUSE","delta":{"dx":-2.0},"position":{"dx":1034.7567138671875,"dy":818.984130859375},"pressure_range":{"upper_bound":1.0},"radius_major":0.5,"radius_minor":0.5,"size":1.0,"viewport_boundary_status":"IN_VIEWPORT"},{"determined_at":"64975","type":"MOUSE","delta":{"dx":-4.5,"dy":-0.5},"position":{"dx":1025.9114990234375,"dy":817.3256225585938},"pressure_range":{"upper_bound":1.0},"radius_major":0.5,"radius_minor":0.5,"size":1.0,"viewport_boundary_status":"IN_VIEWPORT"},{"determined_at":"64990","type":"MOUSE","delta":{"dx":-17.0,"dy":-6.0},"position":{"dx":991.214599609375,"dy":805.4295654296875},"pressure_range":{"upper_bound":1.0},"radius_major":0.5,"radius_minor":0.5,"size":1.0,"viewport_boundary_status":"IN_VIEWPORT"},{"determined_at":"65005","type":"MOUSE","delta":{"dx":-37.5,"dy":-15.5},"position":{"dx":916.9974975585938,"dy":774.6224975585938},"pressure_range":{"upper_bound":1.0},"radius_major":0.5,"radius_minor":0.5,"size":1.0,"viewport_boundary_status":"IN_VIEWPORT"},{"determined_at":"65020","type":"MOUSE","delta":{"dx":-23.5,"dy":-11.0},"position":{"dx":869.3926391601562,"dy":752.5617065429688},"pressure_range":{"upper_bound":1.0},"radius_major":0.5,"radius_minor":0.5,"size":1.0,"viewport_boundary_status":"IN_VIEWPORT"},{"determined_at":"65035","type":"MOUSE","delta":{"dx":-48.0,"dy":-26.0},"position":{"dx":773.9411010742188,"dy":700.9240112304688},"pressure_range":{"upper_bound":1.0},"radius_major":0.5,"radius_minor":0.5,"size":1.0,"viewport_boundary_status":"IN_VIEWPORT"},{"determined_at":"65050","type":"MOUSE","delta":{"dx":-28.5,"dy":-24.5},"position":{"dx":716.57177734375,"dy":651.750244140625},"pressure_range":{"upper_bound":1.0},"radius_major":0.5,"radius_minor":0.5,"size":1.0,"viewport_boundary_status":"IN_VIEWPORT"},{"determined_at":"65065","type":"MOUSE","delta":{"dx":-18.5,"dy":-24.0},"position":{"dx":679.1759033203125,"dy":603.1356201171875},"pressure_range":{"upper_bound":1.0},"radius_major":0.5,"radius_minor":0.5,"size":1.0,"viewport_boundary_status":"IN_VIEWPORT"}],"index":1,"permission_events":[{"determined_at":"64081","sensor_type":"FOCUS_CHANGE","permission_status":"ALLOWED"},{"determined_at":"64081","sensor_type":"KEY_PRESS","permission_status":"ALLOWED"},{"determined_at":"64081","sensor_type":"MOUSE_WHEEL","permission_status":"ALLOWED"},{"determined_at":"64081","sensor_type":"POINTER","permission_status":"ALLOWED"},{"determined_at":"64081","sensor_type":"VIEW_SCROLL","permission_status":"ALLOWED"},{"determined_at":"64081","sensor_type":"TEXT_CHANGE","permission_status":"ALLOWED"}],"viewport_size_events":[{"determined_at":"64081","device_physical_width":"3250","device_physical_height":"3136","device_logical_width":"1625","device_logical_height":"1568","device_pixel_ratio":2.0,"viewport_orientation":"LANDSCAPE_PRIMARY"}],"app_life_cycle_events":[{"determined_at":"64081","app_life_cycle_status":"FOREGROUND"}]},"app_id":"iznJpoSNZiub4WLaukazhQ","credential_id":"goG2ryXNLJ8JYzJvp4YBxL","session_id":"KvSHAcQiZ9bfCJFryXDxqD","server_time_millis":"1659719581937384"}
{"bundle":{"client_time":{"wall_time_millis":"1659719582831","timer_millis":"66081","timer_realtime_millis":"66081"},"pointer_data":[{"determined_at":"65079","type":"MOUSE","delta":{"dx":-10.5,"dy":-14.5},"position":{"dx":658.8012084960938,"dy":574.0288696289062},"pressure_range":{"upper_bound":1.0},"radius_major":0.5,"radius_minor":0.5,"size":1.0,"viewport_boundary_status":"IN_VIEWPORT"},{"determined_at":"65094","type":"MOUSE","delta":{"dx":-11.5,"dy":-19.0},"position":{"dx":635.1285400390625,"dy":536.3677978515625},"pressure_range":{"upper_bound":1.0},"radius_major":0.5,"radius_minor":0.5,"size":1.0,"viewport_boundary_status":"IN_VIEWPORT"},{"determined_at":"65109","type":"MOUSE","delta":{"dx":-8.0,"dy":-12.0},"position":{"dx":619.1805419921875,"dy":512.44580078125},"pressure_range":{"upper_bound":1.0},"radius_major":0.5,"radius_minor":0.5,"size":1.0,"viewport_boundary_status":"IN_VIEWPORT"},{"determined_at":"65124","type":"MOUSE","delta":{"dx":-8.5,"dy":-14.0},"position":{"dx":602.475341796875,"dy":484.60382080078125},"pressure_range":{"upper_bound":1.0},"radius_major":0.5,"radius_minor":0.5,"size":1.0,"viewport_boundary_status":"IN_VIEWPORT"},{"determined_at":"65139","type":"MOUSE","delta":{"dx":-5.0,"dy":-12.5},"position":{"dx":592.9603271484375,"dy":459.518798828125},"pressure_range":{"upper_bound":1.0},"radius_major":0.5,"radius_minor":0.5,"size":1.0,"viewport_boundary_status":"IN_VIEWPORT"},{"determined_at":"65169","type":"MOUSE","delta":{"dx":-0.5,"dy":-12.5},"position":{"dx":591.2745361328125,"dy":434.62298583984375},"pressure_range":{"upper_bound":1.0},"radius_major":0.5,"radius_minor":0.5,"size":1.0,"viewport_boundary_status":"IN_VIEWPORT"},{"determined_at":"65184","type":"MOUSE","delta":{"dx":1.5,"dy":-3.0},"position":{"dx":594.2206420898438,"dy":428.7308349609375},"pressure_range":{"upper_bound":1.0},"radius_major":0.5,"radius_minor":0.5,"size":1.0,"viewport_boundary_status":"IN_VIEWPORT"},{"determined_at":"65199","type":"MOUSE","delta":{"dx":3.5,"dy":-4.5},"position":{"dx":601.5986938476562,"dy":419.50823974609375},"pressure_range":{"upper_bound":1.0},"radius_major":0.5,"radius_minor":0.5,"size":1.0,"viewport_boundary_status":"IN_VIEWPORT"},{"determined_at":"65214","type":"MOUSE","delta":{"dx":4.5,"dy":-3.5},"position":{"dx":610.8212890625,"dy":412.13018798828125},"pressure_range":{"upper_bound":1.0},"radius_major":0.5,"radius_minor":0.5,"size":1.0,"viewport_boundary_status":"IN_VIEWPORT"},{"determined_at":"65229","type":"MOUSE","delta":{"dx":2.5,"dy":-2.0},"position":{"dx":615.52587890625,"dy":408.83697509765625},"pressure_range":{"upper_bound":1.0},"radius_major":0.5,"radius_minor":0.5,"size":1.0,"viewport_boundary_status":"IN_VIEWPORT"},{"determined_at":"65244","type":"MOUSE","delta":{"dx":2.5,"dy":-1.5},"position":{"dx":620.927001953125,"dy":405.3998718261719},"pressure_range":{"upper_bound":1.0},"radius_major":0.5,"radius_minor":0.5,"size":1.0,"viewport_boundary_status":"IN_VIEWPORT","target":{"target_id":"81437fd5-f5c0-405c-8c76-b87ad1726804","target_type":"password"}},{"determined_at":"65260","type":"MOUSE","delta":{"dx":1.0,"dy":-0.5},"position":{"dx":622.5631103515625,"dy":404.7454528808594},"pressure_range":{"upper_bound":1.0},"radius_major":0.5,"radius_minor":0.5,"size":1.0,"viewport_boundary_status":"IN_VIEWPORT","target":{"target_id":"81437fd5-f5c0-405c-8c76-b87ad1726804","target_type":"password"}},{"determined_at":"65274","type":"MOUSE","delta":{"dx":0.5},"position":{"dx":623.095458984375,"dy":404.4792785644531},"pressure_range":{"upper_bound":1.0},"radius_major":0.5,"radius_minor":0.5,"size":1.0,"viewport_boundary_status":"IN_VIEWPORT","target":{"target_id":"81437fd5-f5c0-405c-8c76-b87ad1726804","target_type":"password"}}],"index":2},"app_id":"iznJpoSNZiub4WLaukazhQ","credential_id":"goG2ryXNLJ8JYzJvp4YBxL","session_id":"KvSHAcQiZ9bfCJFryXDxqD","server_time_millis":"1659719582983679"}
{"bundle":{"client_time":{"wall_time_millis":"1659719583836","timer_millis":"67085","timer_realtime_millis":"67085"},"pointer_data":[{"determined_at":"66145","type":"MOUSE","delta":{},"position":{"dx":623.34130859375,"dy":404.4792785644531},"pressure_range":{"upper_bound":1.0},"radius_major":0.5,"radius_minor":0.5,"size":1.0,"viewport_boundary_status":"IN_VIEWPORT","target":{"target_id":"81437fd5-f5c0-405c-8c76-b87ad1726804","target_type":"password"}},{"determined_at":"66159","type":"MOUSE","delta":{},"position":{"dx":623.8736572265625,"dy":404.4792785644531},"pressure_range":{"upper_bound":1.0},"radius_major":0.5,"radius_minor":0.5,"size":1.0,"viewport_boundary_status":"IN_VIEWPORT","target":{"target_id":"81437fd5-f5c0-405c-8c76-b87ad1726804","target_type":"password"}},{"determined_at":"66174","type":"MOUSE","delta":{"dx":2.5},"position":{"dx":628.8228149414062,"dy":404.02935791015625},"pressure_range":{"upper_bound":1.0},"radius_major":0.5,"radius_minor":0.5,"size":1.0,"viewport_boundary_status":"IN_VIEWPORT","target":{"target_id":"81437fd5-f5c0-405c-8c76-b87ad1726804","target_type":"password"}},{"determined_at":"66189","type":"MOUSE","delta":{"dx":18.5,"dy":-4.0},"position":{"dx":665.5023803710938,"dy":396.0986328125},"pressure_range":{"upper_bound":1.0},"radius_major":0.5,"radius_minor":0.5,"size":1.0,"viewport_boundary_status":"IN_VIEWPORT","target":{"target_id":"81437fd5-f5c0-405c-8c76-b87ad1726804","target_type":"password"}},{"determined_at":"66204","type":"MOUSE","delta":{"dx":41.5,"dy":-10.0},"position":{"dx":748.580322265625,"dy":376.04534912109375},"pressure_range":{"upper_bound":1.0},"radius_major":0.5,"radius_minor":0.5,"size":1.0,"viewport_boundary_status":"IN_VIEWPORT","target":{"target_id":"81437fd5-f5c0-405c-8c76-b87ad1726804","target_type":"password"}},{"determined_at":"66219","type":"MOUSE","delta":{"dx":40.5,"dy":-8.0},"position":{"dx":829.3280639648438,"dy":360.46246337890625},"pressure_range":{"upper_bound":1.0},"radius_major":0.5,"radius_minor":0.5,"size":1.0,"viewport_boundary_status":"IN_VIEWPORT","target":{"target_id":"81437fd5-f5c0-405c-8c76-b87ad1726804","target_type":"password"}},{"determined_at":"66234","type":"MOUSE","delta":{"dx":86.5,"dy":-11.5},"position":{"dx":1002.9843139648438,"dy":337.18896484375},"pressure_range":{"upper_bound":1.0},"radius_major":0.5,"radius_minor":0.5,"size":1.0,"viewport_boundary_status":"IN_VIEWPORT"},{"determined_at":"66249","type":"MOUSE","delta":{"dx":94.0,"dy":-9.5},"position":{"dx":1190.6829833984375,"dy":318.9657897949219},"pressure_range":{"upper_bound":1.0},"radius_major":0.5,"radius_minor":0.5,"size":1.0,"viewport_boundary_status":"IN_VIEWPORT"},{"determined_at":"66264","type":"MOUSE","delta":{"dx":66.0,"dy":-5.0},"position":{"dx":1322.1121826171875,"dy":308.98382568359375},"pressure_range":{"upper_bound":1.0},"radius_major":0.5,"radius_minor":0.5,"size":1.0,"viewport_boundary_status":"IN_VIEWPORT"},{"determined_at":"66279","type":"MOUSE","delta":{"dx":93.5,"dy":-3.5},"position":{"dx":1509.810791015625,"dy":301.694580078125},"pressure_range":{"upper_bound":1.0},"radius_major":0.5,"radius_minor":0.5,"size":1.0,"viewport_boundary_status":"IN_VIEWPORT"},{"determined_at":"66295","type":"MOUSE","delta":{},"position":{"dx":1671.7373046875,"dy":299.93450927734375},"pressure_range":{"upper_bound":1.0},"radius_major":0.5,"radius_minor":0.5,"size":1.0,"viewport_boundary_status":"LEAVE_VIEWPORT"}],"index":3},"app_id":"iznJpoSNZiub4WLaukazhQ","credential_id":"goG2ryXNLJ8JYzJvp4YBxL","session_id":"KvSHAcQiZ9bfCJFryXDxqD","server_time_millis":"1659719583941204"}
{"bundle":{"client_time":{"wall_time_millis":"1659719584831","timer_millis":"68081","timer_realtime_millis":"68081"},"pointer_data":[{"determined_at":"67525","type":"MOUSE","delta":{},"position":{"dx":1444.1046142578125,"dy":232.7587890625},"pressure_range":{"upper_bound":1.0},"radius_major":0.5,"radius_minor":0.5,"size":1.0,"viewport_boundary_status":"ENTER_VIEWPORT"},{"determined_at":"67525","type":"MOUSE","delta":{},"position":{"dx":1444.1046142578125,"dy":232.7587890625},"pressure_range":{"upper_bound":1.0},"radius_major":0.5,"radius_minor":0.5,"size":1.0,"viewport_boundary_status":"IN_VIEWPORT"},{"determined_at":"67525","type":"MOUSE","delta":{},"position":{"dx":1444.1046142578125,"dy":232.7587890625},"pressure_range":{"upper_bound":1.0},"radius_major":0.5,"radius_minor":0.5,"size":1.0,"viewport_boundary_status":"LEAVE_VIEWPORT"},{"determined_at":"68004","type":"MOUSE","delta":{},"position":{"dx":651.774169921875,"dy":285.91259765625},"pressure_range":{"upper_bound":1.0},"radius_major":0.5,"radius_minor":0.5,"size":1.0,"viewport_boundary_status":"ENTER_VIEWPORT"},{"determined_at":"68004","type":"MOUSE","delta":{},"position":{"dx":651.774169921875,"dy":285.91259765625},"pressure_range":{"upper_bound":1.0},"radius_major":0.5,"radius_minor":0.5,"size":1.0,"viewport_boundary_status":"IN_VIEWPORT","target":{"target_id":"7f92f988-84f2-4569-a611-922b25ea2660","target_type":"email"}},{"determined_at":"68019","type":"MOUSE","delta":{},"position":{"dx":651.774169921875,"dy":285.3802490234375},"pressure_range":{"upper_bound":1.0},"radius_major":0.5,"radius_minor":0.5,"size":1.0,"viewport_boundary_status":"IN_VIEWPORT","target":{"target_id":"7f92f988-84f2-4569-a611-922b25ea2660","target_type":"email"}},{"determined_at":"68034","type":"MOUSE","delta":{},"position":{"dx":651.774169921875,"dy":285.1343994140625},"pressure_range":{"upper_bound":1.0},"radius_major":0.5,"radius_minor":0.5,"size":1.0,"viewport_boundary_status":"IN_VIEWPORT","target":{"target_id":"7f92f988-84f2-4569-a611-922b25ea2660","target_type":"email"}},{"determined_at":"68049","type":"MOUSE","delta":{"dy":-1.0},"position":{"dx":651.774169921875,"dy":283.9070129394531},"pressure_range":{"upper_bound":1.0},"radius_major":0.5,"radius_minor":0.5,"size":1.0,"viewport_boundary_status":"IN_VIEWPORT","target":{"target_id":"7f92f988-84f2-4569-a611-922b25ea2660","target_type":"email"}},{"determined_at":"68064","type":"MOUSE","delta":{"dx":0.5,"dy":-1.5},"position":{"dx":652.16259765625,"dy":280.7992858886719},"pressure_range":{"upper_bound":1.0},"radius_major":0.5,"radius_minor":0.5,"size":1.0,"viewport_boundary_status":"IN_VIEWPORT","target":{"target_id":"7f92f988-84f2-4569-a611-922b25ea2660","target_type":"email"}}],"index":4},"app_id":"iznJpoSNZiub4WLaukazhQ","credential_id":"goG2ryXNLJ8JYzJvp4YBxL","session_id":"KvSHAcQiZ9bfCJFryXDxqD","server_time_millis":"1659719584937381"}
{"bundle":{"client_time":{"wall_time_millis":"1659719585835","timer_millis":"69085","timer_realtime_millis":"69085"},"pointer_data":[{"determined_at":"68079","type":"MOUSE","delta":{"dx":0.5,"dy":-3.0},"position":{"dx":653.6356811523438,"dy":274.4161071777344},"pressure_range":{"upper_bound":1.0},"radius_major":0.5,"radius_minor":0.5,"size":1.0,"viewport_boundary_status":"IN_VIEWPORT","target":{"target_id":"7f92f988-84f2-4569-a611-922b25ea2660","target_type":"email"}},{"determined_at":"68094","type":"MOUSE","delta":{"dx":0.5,"dy":-2.0},"position":{"dx":654.4534912109375,"dy":270.7357482910156},"pressure_range":{"upper_bound":1.0},"radius_major":0.5,"radius_minor":0.5,"size":1.0,"viewport_boundary_status":"IN_VIEWPORT","target":{"target_id":"7f92f988-84f2-4569-a611-922b25ea2660","target_type":"email"}},{"determined_at":"68109","type":"MOUSE","delta":{"dx":0.5,"dy":-0.5},"position":{"dx":655.1079711914062,"dy":269.09967041015625},"pressure_range":{"upper_bound":1.0},"radius_major":0.5,"radius_minor":0.5,"size":1.0,"viewport_boundary_status":"IN_VIEWPORT","target":{"target_id":"7f92f988-84f2-4569-a611-922b25ea2660","target_type":"email"}},{"determined_at":"68124","type":"MOUSE","delta":{"dx":0.5,"dy":-1.5},"position":{"dx":656.2120361328125,"dy":266.5234680175781},"pressure_range":{"upper_bound":1.0},"radius_major":0.5,"radius_minor":0.5,"size":1.0,"viewport_boundary_status":"IN_VIEWPORT","target":{"target_id":"7f92f988-84f2-4569-a611-922b25ea2660","target_type":"email"}},{"determined_at":"68139","type":"MOUSE","delta":{"dy":-1.0},"position":{"dx":656.866455078125,"dy":264.88739013671875},"pressure_range":{"upper_bound":1.0},"radius_major":0.5,"radius_minor":0.5,"size":1.0,"viewport_boundary_status":"IN_VIEWPORT","target":{"target_id":"7f92f988-84f2-4569-a611-922b25ea2660","target_type":"email"}},{"determined_at":"68170","type":"MOUSE","delta":{"dx":0.5},"position":{"dx":657.3988037109375,"dy":264.02789306640625},"pressure_range":{"upper_bound":1.0},"radius_major":0.5,"radius_minor":0.5,"size":1.0,"viewport_boundary_status":"IN_VIEWPORT","target":{"target_id":"7f92f988-84f2-4569-a611-922b25ea2660","target_type":"email"}},{"determined_at":"68200","type":"MOUSE","buttons":"1","delta":{},"position":{"dx":657.3988037109375,"dy":264.02789306640625},"pressure":0.5,"pressure_range":{"upper_bound":1.0},"radius_major":0.5,"radius_minor":0.5,"size":1.0,"viewport_boundary_status":"IN_VIEWPORT","target":{"target_id":"7f92f988-84f2-4569-a611-922b25ea2660","target_type":"email"}},{"determined_at":"68290","type":"MOUSE","delta":{},"position":{"dx":657.3988037109375,"dy":264.02789306640625},"pressure_range":{"upper_bound":1.0},"radius_major":0.5,"radius_minor":0.5,"size":1.0,"viewport_boundary_status":"IN_VIEWPORT","target":{"target_id":"7f92f988-84f2-4569-a611-922b25ea2660","target_type":"email"}}],"index":5,"text_change_data":[{"determined_at":"69033","target":{"target_id":"7f92f988-84f2-4569-a611-922b25ea2660","target_type":"email"},"focus":true,"masked_text":"s"}],"key_press_data":[{"determined_at":"69029","type":"KEY_DOWN","masked_key":115,"target":{"target_id":"7f92f988-84f2-4569-a611-922b25ea2660","target_type":"email"}}],"focus_change_data":[{"determined_at":"68201","type":"FOCUS_GAINED","target":{"target_id":"7f92f988-84f2-4569-a611-922b25ea2660","target_type":"email"}}],"custom_events":[{"determined_at":"68201","event_name":"targetElementCreated","properties":{"inputName":"email"},"event_key":"7f92f988-84f2-4569-a611-922b25ea2660"}]},"app_id":"iznJpoSNZiub4WLaukazhQ","credential_id":"goG2ryXNLJ8JYzJvp4YBxL","session_id":"KvSHAcQiZ9bfCJFryXDxqD","server_time_millis":"1659719585941923"}
{"bundle":{"client_time":{"wall_time_millis":"1659719586833","timer_millis":"70082","timer_realtime_millis":"70082"},"index":6,"text_change_data":[{"determined_at":"69141","target":{"target_id":"7f92f988-84f2-4569-a611-922b25ea2660","target_type":"email"},"focus":true,"masked_text":"sо"},{"determined_at":"69243","target":{"target_id":"7f92f988-84f2-4569-a611-922b25ea2660","target_type":"email"},"focus":true,"masked_text":"sоɯ"},{"determined_at":"69440","target":{"target_id":"7f92f988-84f2-4569-a611-922b25ea2660","target_type":"email"},"focus":true,"masked_text":"sоɯa"},{"determined_at":"69497","target":{"target_id":"7f92f988-84f2-4569-a611-922b25ea2660","target_type":"email"},"focus":true,"masked_text":"sоɯaт"},{"determined_at":"69606","target":{"target_id":"7f92f988-84f2-4569-a611-922b25ea2660","target_type":"email"},"focus":true,"masked_text":"sоɯaтљ"},{"determined_at":"69803","target":{"target_id":"7f92f988-84f2-4569-a611-922b25ea2660","target_type":"email"},"focus":true,"masked_text":"sоɯaтљǸ"},{"determined_at":"69967","target":{"target_id":"7f92f988-84f2-4569-a611-922b25ea2660","target_type":"email"},"focus":true,"masked_text":"sоɯaтљǸƾ"}],"key_press_data":[{"determined_at":"69119","type":"KEY_UP","masked_key":115,"target":{"target_id":"7f92f988-84f2-4569-a611-922b25ea2660","target_type":"email"}},{"determined_at":"69138","type":"KEY_DOWN","masked_key":1086,"target":{"target_id":"7f92f988-84f2-4569-a611-922b25ea2660","target_type":"email"}},{"determined_at":"69228","type":"KEY_UP","masked_key":1086,"target":{"target_id":"7f92f988-84f2-4569-a611-922b25ea2660","target_type":"email"}},{"determined_at":"69240","type":"KEY_DOWN","masked_key":623,"target":{"target_id":"7f92f988-84f2-4569-a611-922b25ea2660","target_type":"email"}},{"determined_at":"69330","type":"KEY_UP","masked_key":623,"target":{"target_id":"7f92f988-84f2-4569-a611-922b25ea2660","target_type":"email"}},{"determined_at":"69437","type":"KEY_DOWN","masked_key":97,"target":{"target_id":"7f92f988-84f2-4569-a611-922b25ea2660","target_type":"email"}},{"determined_at":"69494","type":"KEY_DOWN","masked_key":1090,"target":{"target_id":"7f92f988-84f2-4569-a611-922b25ea2660","target_type":"email"}},{"determined_at":"69551","type":"KEY_UP","masked_key":97,"target":{"target_id":"7f92f988-84f2-4569-a611-922b25ea2660","target_type":"email"}},{"determined_at":"69592","type":"KEY_UP","masked_key":1090,"target":{"target_id":"7f92f988-84f2-4569-a611-922b25ea2660","target_type":"email"}},{"determined_at":"69603","type":"KEY_DOWN","masked_key":1113,"target":{"target_id":"7f92f988-84f2-4569-a611-922b25ea2660","target_type":"email"}},{"determined_at":"69660","type":"KEY_UP","masked_key":1113,"target":{"target_id":"7f92f988-84f2-4569-a611-922b25ea2660","target_type":"email"}},{"determined_at":"69718","type":"KEY_DOWN","special_key":"Shift","target":{"target_id":"7f92f988-84f2-4569-a611-922b25ea2660","target_type":"email"},"shift_key":true},{"determined_at":"69800","type":"KEY_DOWN","masked_key":504,"target":{"target_id":"7f92f988-84f2-4569-a611-922b25ea2660","target_type":"email"},"shift_key":true},{"determined_at":"69906","type":"KEY_UP","masked_key":504,"target":{"target_id":"7f92f988-84f2-4569-a611-922b25ea2660","target_type":"email"},"shift_key":true},{"determined_at":"69922","type":"KEY_UP","special_key":"Shift","target":{"target_id":"7f92f988-84f2-4569-a611-922b25ea2660","target_type":"email"}},{"determined_at":"69964","type":"KEY_DOWN","masked_key":446,"target":{"target_id":"7f92f988-84f2-4569-a611-922b25ea2660","target_type":"email"}},{"determined_at":"70053","type":"KEY_UP","masked_key":446,"target":{"target_id":"7f92f988-84f2-4569-a611-922b25ea2660","target_type":"email"}}]},"app_id":"iznJpoSNZiub4WLaukazhQ","credential_id":"goG2ryXNLJ8JYzJvp4YBxL","session_id":"KvSHAcQiZ9bfCJFryXDxqD","server_time_millis":"1659719586939659"}
{"bundle":{"client_time":{"wall_time_millis":"1659719587833","timer_millis":"71082","timer_realtime_millis":"71082"},"index":7,"text_change_data":[{"determined_at":"70192","target":{"target_id":"7f92f988-84f2-4569-a611-922b25ea2660","target_type":"email"},"focus":true,"masked_text":"sоɯaтљǸƾо"},{"determined_at":"70371","target":{"target_id":"7f92f988-84f2-4569-a611-922b25ea2660","target_type":"email"},"focus":true,"masked_text":"sоɯaтљǸƾоо"},{"determined_at":"70525","target":{"target_id":"7f92f988-84f2-4569-a611-922b25ea2660","target_type":"email"},"focus":true,"masked_text":"sоɯaтљǸƾоољ"},{"determined_at":"70653","target":{"target_id":"7f92f988-84f2-4569-a611-922b25ea2660","target_type":"email"},"focus":true,"masked_text":"sоɯaтљǸƾоољẝ"},{"determined_at":"70691","target":{"target_id":"7f92f988-84f2-4569-a611-922b25ea2660","target_type":"email"},"focus":true,"masked_text":"sоɯaтљǸƾоољẝЀ"},{"determined_at":"70763","target":{"target_id":"7f92f988-84f2-4569-a611-922b25ea2660","target_type":"email"},"focus":true,"masked_text":"sоɯaтљǸƾоољẝЀљ"},{"determined_at":"70866","target":{"target_id":"7f92f988-84f2-4569-a611-922b25ea2660","target_type":"email"},"focus":true,"masked_text":"sоɯaтљǸƾоољẝЀљẝ"},{"determined_at":"70921","target":{"target_id":"7f92f988-84f2-4569-a611-922b25ea2660","target_type":"email"},"focus":true,"masked_text":"sоɯaтљǸƾоољẝЀљẝЀ"},{"determined_at":"71049","target":{"target_id":"7f92f988-84f2-4569-a611-922b25ea2660","target_type":"email"},"focus":true,"masked_text":"sоɯaтљǸƾоољẝЀљẝЀr"}],"key_press_data":[{"determined_at":"70188","type":"KEY_DOWN","masked_key":1086,"target":{"target_id":"7f92f988-84f2-4569-a611-922b25ea2660","target_type":"email"}},{"determined_at":"70277","type":"KEY_UP","masked_key":1086,"target":{"target_id":"7f92f988-84f2-4569-a611-922b25ea2660","target_type":"email"}},{"determined_at":"70368","type":"KEY_DOWN","masked_key":1086,"target":{"target_id":"7f92f988-84f2-4569-a611-922b25ea2660","target_type":"email"}},{"determined_at":"70441","type":"KEY_UP","masked_key":1086,"target":{"target_id":"7f92f988-84f2-4569-a611-922b25ea2660","target_type":"email"}},{"determined_at":"70521","type":"KEY_DOWN","masked_key":1113,"target":{"target_id":"7f92f988-84f2-4569-a611-922b25ea2660","target_type":"email"}},{"determined_at":"70611","type":"KEY_UP","masked_key":1113,"target":{"target_id":"7f92f988-84f2-4569-a611-922b25ea2660","target_type":"email"}},{"determined_at":"70650","type":"KEY_DOWN","masked_key":7837,"target":{"target_id":"7f92f988-84f2-4569-a611-922b25ea2660","target_type":"email"}},{"determined_at":"70688","type":"KEY_DOWN","masked_key":1024,"target":{"target_id":"7f92f988-84f2-4569-a611-922b25ea2660","target_type":"email"}},{"determined_at":"70748","type":"KEY_UP","masked_key":7837,"target":{"target_id":"7f92f988-84f2-4569-a611-922b25ea2660","target_type":"email"}},{"determined_at":"70759","type":"KEY_DOWN","masked_key":1113,"target":{"target_id":"7f92f988-84f2-4569-a611-922b25ea2660","target_type":"email"}},{"determined_at":"70794","type":"KEY_UP","masked_key":1024,"target":{"target_id":"7f92f988-84f2-4569-a611-922b25ea2660","target_type":"email"}},{"determined_at":"70841","type":"KEY_UP","masked_key":1113,"target":{"target_id":"7f92f988-84f2-4569-a611-922b25ea2660","target_type":"email"}},{"determined_at":"70863","type":"KEY_DOWN","masked_key":7837,"target":{"target_id":"7f92f988-84f2-4569-a611-922b25ea2660","target_type":"email"}},{"determined_at":"70918","type":"KEY_DOWN","masked_key":1024,"target":{"target_id":"7f92f988-84f2-4569-a611-922b25ea2660","target_type":"email"}},{"determined_at":"70961","type":"KEY_UP","masked_key":7837,"target":{"target_id":"7f92f988-84f2-4569-a611-922b25ea2660","target_type":"email"}},{"determined_at":"71032","type":"KEY_UP","masked_key":1024,"target":{"target_id":"7f92f988-84f2-4569-a611-922b25ea2660","target_type":"email"}},{"determined_at":"71046","type":"KEY_DOWN","masked_key":114,"target":{"target_id":"7f92f988-84f2-4569-a611-922b25ea2660","target_type":"email"}}]},"app_id":"iznJpoSNZiub4WLaukazhQ","credential_id":"goG2ryXNLJ8JYzJvp4YBxL","session_id":"KvSHAcQiZ9bfCJFryXDxqD","server_time_millis":"1659719587939844"}
{"bundle":{"client_time":{"wall_time_millis":"1659719588835","timer_millis":"72085","timer_realtime_millis":"72085"},"index":8,"text_change_data":[{"determined_at":"71257","target":{"target_id":"7f92f988-84f2-4569-a611-922b25ea2660","target_type":"email"},"focus":true,"masked_text":"sоɯaтљǸƾоољẝЀљẝЀrѹ"},{"determined_at":"71420","target":{"target_id":"7f92f988-84f2-4569-a611-922b25ea2660","target_type":"email"},"focus":true,"masked_text":"sоɯaтљǸƾоољẝЀљẝЀrѹо"}],"key_press_data":[{"determined_at":"71103","type":"KEY_UP","masked_key":114,"target":{"target_id":"7f92f988-84f2-4569-a611-922b25ea2660","target_type":"email"}},{"determined_at":"71254","type":"KEY_DOWN","masked_key":1145,"target":{"target_id":"7f92f988-84f2-4569-a611-922b25ea2660","target_type":"email"}},{"determined_at":"71310","type":"KEY_UP","masked_key":1145,"target":{"target_id":"7f92f988-84f2-4569-a611-922b25ea2660","target_type":"email"}},{"determined_at":"71417","type":"KEY_DOWN","masked_key":1086,"target":{"target_id":"7f92f988-84f2-4569-a611-922b25ea2660","target_type":"email"}},{"determined_at":"71491","type":"KEY_UP","masked_key":1086,"target":{"target_id":"7f92f988-84f2-4569-a611-922b25ea2660","target_type":"email"}},{"determined_at":"71581","type":"KEY_DOWN","special_key":"Tab","target":{"target_id":"7f92f988-84f2-4569-a611-922b25ea2660","target_type":"email"}},{"determined_at":"71704","type":"KEY_UP","special_key":"Tab","target":{"target_id":"81437fd5-f5c0-405c-8c76-b87ad1726804","target_type":"password"}}],"focus_change_data":[{"determined_at":"71584","type":"FOCUS_LOST","target":{"target_id":"7f92f988-84f2-4569-a611-922b25ea2660","target_type":"email"}},{"determined_at":"71584","type":"FOCUS_GAINED","target":{"target_id":"81437fd5-f5c0-405c-8c76-b87ad1726804","target_type":"password"}}],"custom_events":[{"determined_at":"71584","event_name":"targetElementCreated","properties":{"inputName":"password"},"event_key":"81437fd5-f5c0-405c-8c76-b87ad1726804"}]},"app_id":"iznJpoSNZiub4WLaukazhQ","credential_id":"goG2ryXNLJ8JYzJvp4YBxL","session_id":"KvSHAcQiZ9bfCJFryXDxqD","server_time_millis":"1659719588988895"}
{"bundle":{"client_time":{"wall_time_millis":"1659719589833","timer_millis":"73083","timer_realtime_millis":"73083"},"index":9,"text_change_data":[{"determined_at":"72348","target":{"target_id":"81437fd5-f5c0-405c-8c76-b87ad1726804","target_type":"password"},"focus":true,"masked_text":"į"},{"determined_at":"72600","target":{"target_id":"81437fd5-f5c0-405c-8c76-b87ad1726804","target_type":"password"},"focus":true,"masked_text":"įḙ"},{"determined_at":"72868","target":{"target_id":"81437fd5-f5c0-405c-8c76-b87ad1726804","target_type":"password"},"focus":true,"masked_text":"įḙỷ"},{"determined_at":"73016","target":{"target_id":"81437fd5-f5c0-405c-8c76-b87ad1726804","target_type":"password"},"focus":true,"masked_text":"įḙỷỷ"}],"key_press_data":[{"determined_at":"72258","type":"KEY_DOWN","special_key":"Shift","target":{"target_id":"81437fd5-f5c0-405c-8c76-b87ad1726804","target_type":"password"},"shift_key":true},{"determined_at":"72346","type":"KEY_DOWN","masked_key":303,"target":{"target_id":"81437fd5-f5c0-405c-8c76-b87ad1726804","target_type":"password"},"shift_key":true},{"determined_at":"72436","type":"KEY_UP","masked_key":303,"target":{"target_id":"81437fd5-f5c0-405c-8c76-b87ad1726804","target_type":"password"},"shift_key":true},{"determined_at":"72447","type":"KEY_UP","special_key":"Shift","target":{"target_id":"81437fd5-f5c0-405c-8c76-b87ad1726804","target_type":"password"}},{"determined_at":"72598","type":"KEY_DOWN","masked_key":7705,"target":{"target_id":"81437fd5-f5c0-405c-8c76-b87ad1726804","target_type":"password"}},{"determined_at":"72671","type":"KEY_UP","masked_key":7705,"target":{"target_id":"81437fd5-f5c0-405c-8c76-b87ad1726804","target_type":"password"}},{"determined_at":"72866","type":"KEY_DOWN","masked_key":7927,"target":{"target_id":"81437fd5-f5c0-405c-8c76-b87ad1726804","target_type":"password"}},{"determined_at":"72939","type":"KEY_UP","masked_key":7927,"target":{"target_id":"81437fd5-f5c0-405c-8c76-b87ad1726804","target_type":"password"}},{"determined_at":"73014","type":"KEY_DOWN","masked_key":7927,"target":{"target_id":"81437fd5-f5c0-405c-8c76-b87ad1726804","target_type":"password"}}]},"app_id":"iznJpoSNZiub4WLaukazhQ","credential_id":"goG2ryXNLJ8JYzJvp4YBxL","session_id":"KvSHAcQiZ9bfCJFryXDxqD","server_time_millis":"1659719589939039"}
{"bundle":{"client_time":{"wall_time_millis":"1659719590831","timer_millis":"74081","timer_realtime_millis":"74081"},"pointer_data":[{"determined_at":"73854","type":"MOUSE","delta":{"dy":-0.5},"position":{"dx":657.3988037109375,"dy":263.78204345703125},"pressure_range":{"upper_bound":1.0},"radius_major":0.5,"radius_minor":0.5,"size":1.0,"viewport_boundary_status":"IN_VIEWPORT","target":{"target_id":"7f92f988-84f2-4569-a611-922b25ea2660","target_type":"email"}},{"determined_at":"73869","type":"MOUSE","delta":{},"position":{"dx":657.6447143554688,"dy":263.78204345703125},"pressure_range":{"upper_bound":1.0},"radius_major":0.5,"radius_minor":0.5,"size":1.0,"viewport_boundary_status":"IN_VIEWPORT","target":{"target_id":"7f92f988-84f2-4569-a611-922b25ea2660","target_type":"email"}},{"determined_at":"73884","type":"MOUSE","delta":{},"position":{"dx":657.8905639648438,"dy":263.5361633300781},"pressure_range":{"upper_bound":1.0},"radius_major":0.5,"radius_minor":0.5,"size":1.0,"viewport_boundary_status":"IN_VIEWPORT","target":{"target_id":"7f92f988-84f2-4569-a611-922b25ea2660","target_type":"email"}},{"determined_at":"73900","type":"MOUSE","delta":{"dx":1.0,"dy":-0.5},"position":{"dx":659.9761962890625,"dy":262.49334716796875},"pressure_range":{"upper_bound":1.0},"radius_major":0.5,"radius_minor":0.5,"size":1.0,"viewport_boundary_status":"IN_VIEWPORT","target":{"target_id":"7f92f988-84f2-4569-a611-922b25ea2660","target_type":"email"}},{"determined_at":"73914","type":"MOUSE","delta":{"dx":2.5,"dy":-0.5},"position":{"dx":664.2703857421875,"dy":261.2051086425781},"pressure_range":{"upper_bound":1.0},"radius_major":0.5,"radius_minor":0.5,"size":1.0,"viewport_boundary_status":"IN_VIEWPORT","target":{"target_id":"7f92f988-84f2-4569-a611-922b25ea2660","target_type":"email"}},{"determined_at":"73930","type":"MOUSE","delta":{"dx":1.5},"position":{"dx":667.9507446289062,"dy":261.2051086425781},"pressure_range":{"upper_bound":1.0},"radius_major":0.5,"radius_minor":0.5,"size":1.0,"viewport_boundary_status":"IN_VIEWPORT","target":{"target_id":"7f92f988-84f2-4569-a611-922b25ea2660","target_type":"email"}},{"determined_at":"73944","type":"MOUSE","delta":{},"position":{"dx":667.9507446289062,"dy":261.7374572753906},"pressure_range":{"upper_bound":1.0},"radius_major":0.5,"radius_minor":0.5,"size":1.0,"viewport_boundary_status":"IN_VIEWPORT","target":{"target_id":"7f92f988-84f2-4569-a611-922b25ea2660","target_type":"email"}},{"determined_at":"73959","type":"MOUSE","delta":{"dy":1.0},"position":{"dx":667.62353515625,"dy":263.37353515625},"pressure_range":{"upper_bound":1.0},"radius_major":0.5,"radius_minor":0.5,"size":1.0,"viewport_boundary_status":"IN_VIEWPORT","target":{"target_id":"7f92f988-84f2-4569-a611-922b25ea2660","target_type":"email"}},{"determined_at":"73974","type":"MOUSE","delta":{"dx":-1.5,"dy":2.5},"position":{"dx":664.80078125,"dy":268.5485534667969},"pressure_range":{"upper_bound":1.0},"radius_major":0.5,"radius_minor":0.5,"size":1.0,"viewport_boundary_status":"IN_VIEWPORT","target":{"target_id":"7f92f988-84f2-4569-a611-922b25ea2660","target_type":"email"}},{"determined_at":"73989","type":"MOUSE","delta":{"dx":-2.0,"dy":4.0},"position":{"dx":660.9310302734375,"dy":276.84088134765625},"pressure_range":{"upper_bound":1.0},"radius_major":0.5,"radius_minor":0.5,"size":1.0,"viewport_boundary_status":"IN_VIEWPORT","target":{"target_id":"7f92f988-84f2-4569-a611-922b25ea2660","target_type":"email"}},{"determined_at":"74019","type":"MOUSE","delta":{"dx":-1.5,"dy":7.0},"position":{"dx":657.4929809570312,"dy":290.8840637207031},"pressure_range":{"upper_bound":1.0},"radius_major":0.5,"radius_minor":0.5,"size":1.0,"viewport_boundary_status":"IN_VIEWPORT","target":{"target_id":"7f92f988-84f2-4569-a611-922b25ea2660","target_type":"email"}},{"determined_at":"74034","type":"MOUSE","delta":{"dy":4.0},"position":{"dx":657.4929809570312,"dy":298.0463562011719},"pressure_range":{"upper_bound":1.0},"radius_major":0.5,"radius_minor":0.5,"size":1.0,"viewport_boundary_status":"IN_VIEWPORT","target":{"target_id":"7f92f988-84f2-4569-a611-922b25ea2660","target_type":"email"}},{"determined_at":"74049","type":"MOUSE","delta":{"dx":1.0,"dy":4.5},"position":{"dx":659.21337890625,"dy":307.7953796386719},"pressure_range":{"upper_bound":1.0},"radius_major":0.5,"radius_minor":0.5,"size":1.0,"viewport_boundary_status":"IN_VIEWPORT"},{"determined_at":"74064","type":"MOUSE","delta":{"dx":0.5,"dy":2.5},"position":{"dx":660.5631713867188,"dy":312.7445373535156},"pressure_range":{"upper_bound":1.0},"radius_major":0.5,"radius_minor":0.5,"size":1.0,"viewport_boundary_status":"IN_VIEWPORT"}],"index":10,"text_change_data":[{"determined_at":"73141","target":{"target_id":"81437fd5-f5c0-405c-8c76-b87ad1726804","target_type":"password"},"focus":true,"masked_text":"įḙỷỷǈ"},{"determined_at":"73248","target":{"target_id":"81437fd5-f5c0-405c-8c76-b87ad1726804","target_type":"password"},"focus":true,"masked_text":"įḙỷỷǈỬ"},{"determined_at":"73515","target":{"target_id":"81437fd5-f5c0-405c-8c76-b87ad1726804","target_type":"password"},"focus":true,"masked_text":"įḙỷỷǈỬổ"},{"determined_at":"73573","target":{"target_id":"81437fd5-f5c0-405c-8c76-b87ad1726804","target_type":"password"},"focus":true,"masked_text":"įḙỷỷǈỬổṄ"},{"determined_at":"73638","target":{"target_id":"81437fd5-f5c0-405c-8c76-b87ad1726804","target_type":"password"},"focus":true,"masked_text":"įḙỷỷǈỬổṄẳ"}],"key_press_data":[{"determined_at":"73120","type":"KEY_UP","masked_key":7927,"target":{"target_id":"81437fd5-f5c0-405c-8c76-b87ad1726804","target_type":"password"}},{"determined_at":"73139","type":"KEY_DOWN","masked_key":456,"target":{"target_id":"81437fd5-f5c0-405c-8c76-b87ad1726804","target_type":"password"}},{"determined_at":"73246","type":"KEY_DOWN","masked_key":7916,"target":{"target_id":"81437fd5-f5c0-405c-8c76-b87ad1726804","target_type":"password"}},{"determined_at":"73286","type":"KEY_UP","masked_key":456,"target":{"target_id":"81437fd5-f5c0-405c-8c76-b87ad1726804","target_type":"password"}},{"determined_at":"73344","type":"KEY_UP","masked_key":7916,"target":{"target_id":"81437fd5-f5c0-405c-8c76-b87ad1726804","target_type":"password"}},{"determined_at":"73513","type":"KEY_DOWN","masked_key":7893,"target":{"target_id":"81437fd5-f5c0-405c-8c76-b87ad1726804","target_type":"password"}},{"determined_at":"73571","type":"KEY_DOWN","masked_key":7748,"target":{"target_id":"81437fd5-f5c0-405c-8c76-b87ad1726804","target_type":"password"}},{"determined_at":"73628","type":"KEY_UP","masked_key":7893,"target":{"target_id":"81437fd5-f5c0-405c-8c76-b87ad1726804","target_type":"password"}},{"determined_at":"73636","type":"KEY_DOWN","masked_key":7859,"target":{"target_id":"81437fd5-f5c0-405c-8c76-b87ad1726804","target_type":"password"}},{"determined_at":"73709","type":"KEY_UP","masked_key":7748,"target":{"target_id":"81437fd5-f5c0-405c-8c76-b87ad1726804","target_type":"password"}},{"determined_at":"73767","type":"KEY_UP","masked_key":7859,"target":{"target_id":"81437fd5-f5c0-405c-8c76-b87ad1726804","target_type":"password"}},{"determined_at":"73915","type":"KEY_DOWN","special_key":"Shift","target":{"target_id":"81437fd5-f5c0-405c-8c76-b87ad1726804","target_type":"password"},"shift_key":true}]},"app_id":"iznJpoSNZiub4WLaukazhQ","credential_id":"goG2ryXNLJ8JYzJvp4YBxL","session_id":"KvSHAcQiZ9bfCJFryXDxqD","server_time_millis":"1659719590939426"}
{"bundle":{"client_time":{"wall_time_millis":"1659719591462","timer_millis":"74711","timer_realtime_millis":"74711"},"pointer_data":[{"determined_at":"74079","type":"MOUSE","delta":{"dx":1.0,"dy":4.0},"position":{"dx":662.6919555664062,"dy":320.72747802734375},"pressure_range":{"upper_bound":1.0},"radius_major":0.5,"radius_minor":0.5,"size":1.0,"viewport_boundary_status":"IN_VIEWPORT"},{"determined_at":"74094","type":"MOUSE","delta":{"dx":0.5,"dy":2.5},"position":{"dx":663.121337890625,"dy":325.0216369628906},"pressure_range":{"upper_bound":1.0},"radius_major":0.5,"radius_minor":0.5,"size":1.0,"viewport_boundary_status":"IN_VIEWPORT"},{"determined_at":"74109","type":"MOUSE","delta":{"dy":1.5},"position":{"dx":663.121337890625,"dy":328.7019958496094},"pressure_range":{"upper_bound":1.0},"radius_major":0.5,"radius_minor":0.5,"size":1.0,"viewport_boundary_status":"IN_VIEWPORT"},{"determined_at":"74124","type":"MOUSE","delta":{"dy":1.5},"position":{"dx":663.121337890625,"dy":331.2781982421875},"pressure_range":{"upper_bound":1.0},"radius_major":0.5,"radius_minor":0.5,"size":1.0,"viewport_boundary_status":"IN_VIEWPORT"},{"determined_at":"74139","type":"MOUSE","delta":{"dy":1.0},"position":{"dx":663.121337890625,"dy":333.8543701171875},"pressure_range":{"upper_bound":1.0},"radius_major":0.5,"radius_minor":0.5,"size":1.0,"viewport_boundary_status":"IN_VIEWPORT"},{"determined_at":"74169","type":"MOUSE","delta":{"dx":3.0,"dy":3.5},"position":{"dx":669.3797607421875,"dy":340.3372802734375},"pressure_range":{"upper_bound":1.0},"radius_major":0.5,"radius_minor":0.5,"size":1.0,"viewport_boundary_status":"IN_VIEWPORT"},{"determined_at":"74184","type":"MOUSE","delta":{"dx":5.5,"dy":3.0},"position":{"dx":680.81982421875,"dy":346.05731201171875},"pressure_range":{"upper_bound":1.0},"radius_major":0.5,"radius_minor":0.5,"size":1.0,"viewport_boundary_status":"IN_VIEWPORT","target":{"target_id":"81437fd5-f5c0-405c-8c76-b87ad1726804","target_type":"password"}},{"determined_at":"74199","type":"MOUSE","delta":{"dx":8.5,"dy":2.5},"position":{"dx":697.3491821289062,"dy":351.806640625},"pressure_range":{"upper_bound":1.0},"radius_major":0.5,"radius_minor":0.5,"size":1.0,"viewport_boundary_status":"IN_VIEWPORT","target":{"target_id":"81437fd5-f5c0-405c-8c76-b87ad1726804","target_type":"password"}},{"determined_at":"74214","type":"MOUSE","delta":{"dx":9.0,"dy":2.5},"position":{"dx":715.0972290039062,"dy":356.983154296875},"pressure_range":{"upper_bound":1.0},"radius_major":0.5,"radius_minor":0.5,"size":1.0,"viewport_boundary_status":"IN_VIEWPORT","target":{"target_id":"81437fd5-f5c0-405c-8c76-b87ad1726804","target_type":"password"}},{"determined_at":"74229","type":"MOUSE","delta":{"dx":5.5,"dy":1.5},"position":{"dx":726.7791748046875,"dy":359.4425048828125},"pressure_range":{"upper_bound":1.0},"radius_major":0.5,"radius_minor":0.5,"size":1.0,"viewport_boundary_status":"IN_VIEWPORT","target":{"target_id":"81437fd5-f5c0-405c-8c76-b87ad1726804","target_type":"password"}},{"determined_at":"74244","type":"MOUSE","delta":{"dx":13.5,"dy":2.0},"position":{"dx":753.59423828125,"dy":363.7674865722656},"pressure_range":{"upper_bound":1.0},"radius_major":0.5,"radius_minor":0.5,"size":1.0,"viewport_boundary_status":"IN_VIEWPORT","target":{"target_id":"81437fd5-f5c0-405c-8c76-b87ad1726804","target_type":"password"}},{"determined_at":"74260","type":"MOUSE","delta":{"dx":23.0,"dy":4.5},"position":{"dx":799.67919921875,"dy":372.54559326171875},"pressure_range":{"upper_bound":1.0},"radius_major":0.5,"radius_minor":0.5,"size":1.0,"viewport_boundary_status":"IN_VIEWPORT","target":{"target_id":"81437fd5-f5c0-405c-8c76-b87ad1726804","target_type":"password"}},{"determined_at":"74274","type":"MOUSE","delta":{"dx":8.5,"dy":1.5},"position":{"dx":816.9271850585938,"dy":375.4202575683594},"pressure_range":{"upper_bound":1.0},"radius_major":0.5,"radius_minor":0.5,"size":1.0,"viewport_boundary_status":"IN_VIEWPORT","target":{"target_id":"81437fd5-f5c0-405c-8c76-b87ad1726804","target_type":"password"}},{"determined_at":"74290","type":"MOUSE","delta":{"dx":19.0,"dy":5.0},"position":{"dx":854.3888549804688,"dy":385.5450134277344},"pressure_range":{"upper_bound":1.0},"radius_major":0.5,"radius_minor":0.5,"size":1.0,"viewport_boundary_status":"IN_VIEWPORT","target":{"target_id":"81437fd5-f5c0-405c-8c76-b87ad1726804","target_type":"password"}},{"determined_at":"74320","type":"MOUSE","delta":{"dx":29.0,"dy":11.5},"position":{"dx":912.2257080078125,"dy":408.4520263671875},"pressure_range":{"upper_bound":1.0},"radius_major":0.5,"radius_minor":0.5,"size":1.0,"viewport_boundary_status":"IN_VIEWPORT"},{"determined_at":"74334","type":"MOUSE","delta":{"dx":8.0,"dy":4.5},"position":{"dx":928.4947509765625,"dy":417.3260498046875},"pressure_range":{"upper_bound":1.0},"radius_major":0.5,"radius_minor":0.5,"size":1.0,"viewport_boundary_status":"IN_VIEWPORT"},{"determined_at":"74350","type":"MOUSE","delta":{"dx":9.5,"dy":6.5},"position":{"dx":947.7462768554688,"dy":430.160400390625},"pressure_range":{"upper_bound":1.0},"radius_major":0.5,"radius_minor":0.5,"size":1.0,"viewport_boundary_status":"IN_VIEWPORT"},{"determined_at":"74364","type":"MOUSE","delta":{"dx":8.0,"dy":5.0},"position":{"dx":963.2758178710938,"dy":440.513427734375},"pressure_range":{"upper_bound":1.0},"radius_major":0.5,"radius_minor":0.5,"size":1.0,"viewport_boundary_status":"IN_VIEWPORT","target":{"target_id":"fdd26c13-7108-4247-8f08-0e9a03c5d0b1","target_type":"submit"}},{"determined_at":"74379","type":"MOUSE","delta":{"dx":5.5,"dy":3.5},"position":{"dx":974.0802612304688,"dy":447.50457763671875},"pressure_range":{"upper_bound":1.0},"radius_major":0.5,"radius_minor":0.5,"size":1.0,"viewport_boundary_status":"IN_VIEWPORT","target":{"target_id":"fdd26c13-7108-4247-8f08-0e9a03c5d0b1","target_type":"submit"}},{"determined_at":"74394","type":"MOUSE","delta":{"dx":2.0,"dy":1.5},"position":{"dx":978.5795288085938,"dy":450.2041015625},"pressure_range":{"upper_bound":1.0},"radius_major":0.5,"radius_minor":0.5,"size":1.0,"viewport_boundary_status":"IN_VIEWPORT","target":{"target_id":"fdd26c13-7108-4247-8f08-0e9a03c5d0b1","target_type":"submit"}},{"determined_at":"74409","type":"MOUSE","delta":{"dx":0.5,"dy":0.5},"position":{"dx":979.888427734375,"dy":451.185791015625},"pressure_range":{"upper_bound":1.0},"radius_major":0.5,"radius_minor":0.5,"size":1.0,"viewport_boundary_status":"IN_VIEWPORT","target":{"target_id":"fdd26c13-7108-4247-8f08-0e9a03c5d0b1","target_type":"submit"}},{"determined_at":"74424","type":"MOUSE","delta":{"dx":0.5},"position":{"dx":980.13427734375,"dy":451.185791015625},"pressure_range":{"upper_bound":1.0},"radius_major":0.5,"radius_minor":0.5,"size":1.0,"viewport_boundary_status":"IN_VIEWPORT","target":{"target_id":"fdd26c13-7108-4247-8f08-0e9a03c5d0b1","target_type":"submit"}},{"determined_at":"74454","type":"MOUSE","delta":{},"position":{"dx":980.380126953125,"dy":451.185791015625},"pressure_range":{"upper_bound":1.0},"radius_major":0.5,"radius_minor":0.5,"size":1.0,"viewport_boundary_status":"IN_VIEWPORT","target":{"target_id":"fdd26c13-7108-4247-8f08-0e9a03c5d0b1","target_type":"submit"}},{"determined_at":"74469","type":"MOUSE","delta":{},"position":{"dx":980.6259765625,"dy":451.185791015625},"pressure_range":{"upper_bound":1.0},"radius_major":0.5,"radius_minor":0.5,"size":1.0,"viewport_boundary_status":"IN_VIEWPORT","target":{"target_id":"fdd26c13-7108-4247-8f08-0e9a03c5d0b1","target_type":"submit"}},{"determined_at":"74484","type":"MOUSE","delta":{},"position":{"dx":980.8718872070312,"dy":451.431640625},"pressure_range":{"upper_bound":1.0},"radius_major":0.5,"radius_minor":0.5,"size":1.0,"viewport_boundary_status":"IN_VIEWPORT","target":{"target_id":"fdd26c13-7108-4247-8f08-0e9a03c5d0b1","target_type":"submit"}},{"determined_at":"74499","type":"MOUSE","delta":{"dx":1.0},"position":{"dx":982.0992431640625,"dy":451.73846435546875},"pressure_range":{"upper_bound":1.0},"radius_major":0.5,"radius_minor":0.5,"size":1.0,"viewport_boundary_status":"IN_VIEWPORT","target":{"target_id":"fdd26c13-7108-4247-8f08-0e9a03c5d0b1","target_type":"submit"}},{"determined_at":"74514","type":"MOUSE","delta":{"dx":0.5,"dy":0.5},"position":{"dx":983.32666015625,"dy":452.0452880859375},"pressure_range":{"upper_bound":1.0},"radius_major":0.5,"radius_minor":0.5,"size":1.0,"viewport_boundary_status":"IN_VIEWPORT","target":{"target_id":"fdd26c13-7108-4247-8f08-0e9a03c5d0b1","target_type":"submit"}},{"determined_at":"74529","type":"MOUSE","delta":{"dx":0.5},"position":{"dx":984.1861572265625,"dy":452.0452880859375},"pressure_range":{"upper_bound":1.0},"radius_major":0.5,"radius_minor":0.5,"size":1.0,"viewport_boundary_status":"IN_VIEWPORT","target":{"target_id":"fdd26c13-7108-4247-8f08-0e9a03c5d0b1","target_type":"submit"}},{"determined_at":"74544","type":"MOUSE","delta":{},"position":{"dx":984.4320068359375,"dy":452.0452880859375},"pressure_range":{"upper_bound":1.0},"radius_major":0.5,"radius_minor":0.5,"size":1.0,"viewport_boundary_status":"IN_VIEWPORT","target":{"target_id":"fdd26c13-7108-4247-8f08-0e9a03c5d0b1","target_type":"submit"}},{"determined_at":"74574","type":"MOUSE","delta":{},"position":{"dx":984.6778564453125,"dy":452.0452880859375},"pressure_range":{"upper_bound":1.0},"radius_major":0.5,"radius_minor":0.5,"size":1.0,"viewport_boundary_status":"IN_VIEWPORT","target":{"target_id":"fdd26c13-7108-4247-8f08-0e9a03c5d0b1","target_type":"submit"}},{"determined_at":"74589","type":"MOUSE","delta":{},"position":{"dx":984.9237060546875,"dy":452.0452880859375},"pressure_range":{"upper_bound":1.0},"radius_major":0.5,"radius_minor":0.5,"size":1.0,"viewport_boundary_status":"IN_VIEWPORT","target":{"target_id":"fdd26c13-7108-4247-8f08-0e9a03c5d0b1","target_type":"submit"}},{"determined_at":"74604","type":"MOUSE","delta":{"dx":0.5},"position":{"dx":985.1696166992188,"dy":452.0452880859375},"pressure_range":{"upper_bound":1.0},"radius_major":0.5,"radius_minor":0.5,"size":1.0,"viewport_boundary_status":"IN_VIEWPORT","target":{"target_id":"fdd26c13-7108-4247-8f08-0e9a03c5d0b1","target_type":"submit"}},{"determined_at":"74619","type":"MOUSE","delta":{},"position":{"dx":985.4154663085938,"dy":452.0452880859375},"pressure_range":{"upper_bound":1.0},"radius_major":0.5,"radius_minor":0.5,"size":1.0,"viewport_boundary_status":"IN_VIEWPORT","target":{"target_id":"fdd26c13-7108-4247-8f08-0e9a03c5d0b1","target_type":"submit"}},{"determined_at":"74650","type":"MOUSE","buttons":"1","delta":{},"position":{"dx":985.4154663085938,"dy":452.0452880859375},"pressure":0.5,"pressure_range":{"upper_bound":1.0},"radius_major":0.5,"radius_minor":0.5,"size":1.0,"viewport_boundary_status":"IN_VIEWPORT","target":{"target_id":"fdd26c13-7108-4247-8f08-0e9a03c5d0b1","target_type":"submit"}},{"determined_at":"74709","type":"MOUSE","delta":{},"position":{"dx":985.4154663085938,"dy":452.0452880859375},"pressure_range":{"upper_bound":1.0},"radius_major":0.5,"radius_minor":0.5,"size":1.0,"viewport_boundary_status":"IN_VIEWPORT","target":{"target_id":"fdd26c13-7108-4247-8f08-0e9a03c5d0b1","target_type":"submit"}}],"index":11,"text_change_data":[{"determined_at":"74146","target":{"target_id":"81437fd5-f5c0-405c-8c76-b87ad1726804","target_type":"password"},"focus":true,"masked_text":"įḙỷỷǈỬổṄẳz"}],"key_press_data":[{"determined_at":"74144","type":"KEY_DOWN","masked_key":122,"target":{"target_id":"81437fd5-f5c0-405c-8c76-b87ad1726804","target_type":"password"},"shift_key":true},{"determined_at":"74283","type":"KEY_UP","masked_key":122,"target":{"target_id":"81437fd5-f5c0-405c-8c76-b87ad1726804","target_type":"password"},"shift_key":true},{"determined_at":"74332","type":"KEY_UP","special_key":"Shift","target":{"target_id":"81437fd5-f5c0-405c-8c76-b87ad1726804","target_type":"password"}}],"focus_change_data":[{"determined_at":"74651","type":"FOCUS_LOST","target":{"target_id":"81437fd5-f5c0-405c-8c76-b87ad1726804","target_type":"password"}}]},"app_id":"iznJpoSNZiub4WLaukazhQ","credential_id":"goG2ryXNLJ8JYzJvp4YBxL","session_id":"KvSHAcQiZ9bfCJFryXDxqD","server_time_millis":"1659719591578261"}
